HISTORY.txt
LICENSE.txt
MANIFEST.in
README.md
setup.cfg
setup.py
sparc/__init__.py
sparc.git.egg-info/PKG-INFO
sparc.git.egg-info/SOURCES.txt
sparc.git.egg-info/dependency_links.txt
sparc.git.egg-info/entry_points.txt
sparc.git.egg-info/namespace_packages.txt
sparc.git.egg-info/not-zip-safe
sparc.git.egg-info/requires.txt
sparc.git.egg-info/top_level.txt
sparc/git/__init__.py
sparc/git/configure.zcml
sparc/git/ftesting.zcml
sparc/git/interfaces.py
sparc/git/testing.py
sparc/git/url.py
sparc/git/repos/__init__.py
sparc/git/repos/base_dir.py
sparc/git/repos/configure.zcml
sparc/git/repos/interfaces.py
sparc/git/repos/testing.py
sparc/git/repos/stash/__init__.py
sparc/git/repos/stash/configure.zcml
sparc/git/repos/stash/interfaces.py
sparc/git/repos/stash/repos.py
sparc/git/repos/stash/testing.py
sparc/git/repos/stash/tests/__init__.py
sparc/git/repos/stash/tests/test_repos.py
sparc/git/repos/tests/__init__.py
sparc/git/repos/tests/test_base_dir.py
sparc/git/tests/__init__.py
sparc/git/tests/test_url.py